<?xml version="1.0" ?>
<BEBaseFoundation pageID="20395" isTemplate="1">
    <breadcrumb>
        <element level="1">
            <headline><![CDATA[홈]]></headline>
            <href><![CDATA[/ko/index.xml]]></href>
        </element>
<element level="2">
            <headline><![CDATA[Business Events]]></headline>
            <href><![CDATA[/ko/21974.ignore]]></href>
        </element>
<element level="4">
            <headline><![CDATA[Where to go]]></headline>
            <href><![CDATA[/businessevents/kor/where-to-go.xml]]></href>
        </element>
<element level="5">
            <headline><![CDATA[Melbourne]]></headline>
            <href><![CDATA[/businessevents/kor/where-to-go/melbourne.xml]]></href>
        </element>
<element level="6">
            <headline><![CDATA[Venues]]></headline>
            <href><![CDATA[/businessevents/kor/where-to-go/melbourne/venues.xml]]></href>
        </element>

    </breadcrumb>
    <hdlPageTitle><![CDATA[Venues]]></hdlPageTitle>
    <img_background><![CDATA[]]></img_background>
    <opt_HideInBreadcrumbs><![CDATA[Show]]></opt_HideInBreadcrumbs>
    <opt_not_in_sitemap><![CDATA[No]]></opt_not_in_sitemap>
    <opt_show_in_navigation><![CDATA[Show]]></opt_show_in_navigation>
    <stf_MetaKeywords><![CDATA[]]></stf_MetaKeywords>
    <stf_meta_keywords><![CDATA[여행 일정, 사진, 호텔, 행사, 사례 연구, 행사장, 이벤트, 멜버른]]></stf_meta_keywords>
    <stf_meta_description><![CDATA[비즈니스 행사 개최를 위한 멜버른 정보를 찾아보세요. 행사 계획에 필요한 여행 일정, 사례 연구, 이미지 및 기타 유용한 툴도 참고하세요.]]></stf_meta_description>
    <stf_NavSubHeader><![CDATA[]]></stf_NavSubHeader>
    <stf_NavTitle><![CDATA[행사장 ]]></stf_NavTitle>
    <stf_PageTitle><![CDATA[멜버른 - 행사장]]></stf_PageTitle>
    <conMainContent>
        <BELayoutT5 isTemplate="1">
    <img_Event><![CDATA[]]></img_Event>
    <stf_EventDetails><![CDATA[93rd Annual Lions International Convention 2010]]></stf_EventDetails> 
    <stf_EventHeader><![CDATA[Event:]]></stf_EventHeader>
    <stf_galleryheader><![CDATA[GALLERY]]></stf_galleryheader> 
    <stf_header><![CDATA[멜번 ]]></stf_header>
    <stf_highlight><![CDATA[HIGHLIGHT]]></stf_highlight>
    <stf_subheader><![CDATA[행사장]]></stf_subheader>
    <txt_HighLight><![CDATA[]]></txt_HighLight>
    <txt_Summary><![CDATA[]]></txt_Summary> 
    <con_Maincontent>
        <BEGenericHeaderAndConentBody isTemplate="1">
    <hdl_headline><![CDATA[Header and Content Body 2816 - Melb venues]]></hdl_headline>
    <img_DateIcon><![CDATA[]]></img_DateIcon> 
    <img_DestinationIcon><![CDATA[]]></img_DestinationIcon>
    <img_EventTypeIcon><![CDATA[]]></img_EventTypeIcon> 
    <img_DurationIcon><![CDATA[]]></img_DurationIcon> 
    <opt_CaseStudy><![CDATA[0]]></opt_CaseStudy> 
    <stf_author><![CDATA[]]></stf_author>
    <stf_DateText><![CDATA[]]></stf_DateText>
    <stf_DelegatesText><![CDATA[]]></stf_DelegatesText>
    <stf_DestinationText><![CDATA[]]></stf_DestinationText>
    <stf_EventTypeText><![CDATA[]]></stf_EventTypeText>
    <stf_Header><![CDATA[]]></stf_Header>
    <stf_quote><![CDATA[]]></stf_quote>
    <stf_Title><![CDATA[행사장]]></stf_Title>
    <txt_HTML><![CDATA[멜번 전역의 훌륭한 행사장 중 선택할 수 있습니다.
        <p>원하는 정보를 찾기 어려우면, <a href="/businessevents/kor/how-we-can-help/Find-your-local-contact.xml" target="_blank">지역 호주 관광청 담당자에게 문의하시기 바랍니다</a>.</p>]]></txt_HTML> 
</BEGenericHeaderAndConentBody><BEGenericLightboxGallery isTemplate="1">
    <con_gallery_items>
        <BEListingItemLightbox isTemplate="1">
    <stf_ItemTeaserText><![CDATA[세계 유일의 6성급 그린 스타 등급 컨벤션 센터로서 최신 기술과 놀라운 공간을 자랑합니다.]]></stf_ItemTeaserText>
    <anc_ReadMoreLink><![CDATA[]]></anc_ReadMoreLink>
    <img_ItemImage><![CDATA[/contentimages/business-events/Thumb-med-Melbourne/AAP_MCEC_outside.jpg]]></img_ItemImage>
    <img_LightboxImage><![CDATA[<img src="/contentimages/business-events/Light-box-Melbourne/AAP_MCEC_outside.jpg" alt="Melbourne Convention and Exhibition Centre" class="primary" />]]></img_LightboxImage>
    <stf_ItemReadMoreLinkText><![CDATA[자세히 알아보기]]></stf_ItemReadMoreLinkText>
    <stf_ItemTitle><![CDATA[멜번 컨벤션 &amp; 전시 센터(Melbourne Convention &amp; Exhibition Centre) ]]></stf_ItemTitle>
    <stf_LightboxEmailAddress><![CDATA[salesenquiries@mcec.com.au]]></stf_LightboxEmailAddress>
    <stf_LightboxEmailLabel><![CDATA[이메일]]></stf_LightboxEmailLabel>
    <stf_LightboxPartnerId><![CDATA[Melbourne Convention and Exhibition Centre]]></stf_LightboxPartnerId>
    <stf_LightboxWebsiteLabel><![CDATA[홈페이지]]></stf_LightboxWebsiteLabel>
    <stf_LightboxWebsiteURL><![CDATA[www.mcec.com.au]]></stf_LightboxWebsiteURL>
    <txt_LightboxContentBody><![CDATA[<div class="head">
        <h4>
        <p>멜번 컨벤션 &amp; 전시 센터(Melbourne Convention &amp; Exhibition Centre) </p>
        </h4>
        </div>
        <p>세계 유일의 6성급 그린 스타 등급 컨벤션 센터로서 최신 기술과 놀라운 공간을 자랑합니다.</p>
        <ul>
            <li><strong>전화: </strong>+61 3 9235 8210</li>
            <li><strong>팩스:</strong> +61 3 9235 8201</li>
        </ul>]]></txt_LightboxContentBody>
</BEListingItemLightbox><BEListingItemLightbox isTemplate="1">
    <stf_ItemTeaserText><![CDATA[복싱데이 경기(Boxing Day Test)가 벌어지는 경기장 너머로 보이는 도시 스카이라인이 아름다운 최고의 기능 센터입니다. ]]></stf_ItemTeaserText>
    <anc_ReadMoreLink><![CDATA[]]></anc_ReadMoreLink>
    <img_ItemImage><![CDATA[/contentimages/business-events/Thumb-med-Melbourne/TABE_015276_MCG.jpg]]></img_ItemImage>
    <img_LightboxImage><![CDATA[<img src="/contentimages/business-events/Light-box-Melbourne/TABE_015276_MCG.jpg" alt="The Melbourne Cricket Ground" class="primary" />]]></img_LightboxImage>
    <stf_ItemReadMoreLinkText><![CDATA[자세히 알아보기]]></stf_ItemReadMoreLinkText>
    <stf_ItemTitle><![CDATA[멜번 크리켓 경기장(Melbourne Cricket Ground)]]></stf_ItemTitle>
    <stf_LightboxEmailAddress><![CDATA[functions.mcg@epicure.com.au]]></stf_LightboxEmailAddress>
    <stf_LightboxEmailLabel><![CDATA[이메일]]></stf_LightboxEmailLabel>
    <stf_LightboxPartnerId><![CDATA[The Melbourne Cricket Ground]]></stf_LightboxPartnerId>
    <stf_LightboxWebsiteLabel><![CDATA[홈페이지]]></stf_LightboxWebsiteLabel>
    <stf_LightboxWebsiteURL><![CDATA[www.epicure.com.au/Venues/MCG-Home.htm]]></stf_LightboxWebsiteURL>
    <txt_LightboxContentBody><![CDATA[<div class="head">
        <h4>멜번 크리켓 경기장(Melbourne Cricket Ground)</h4>
        <p>복싱데이 경기(Boxing Day Test)가 벌어지는 경기장 너머로 보이는 도시 스카이라인이 아름다운 최고의 기능 센터입니다. </p>
        </div>
        <ul>
            <li><strong>전화: </strong>+61 3 9284 2340</li>
            <li><strong>팩스:</strong> +61 3 9650 4348</li>
        </ul>]]></txt_LightboxContentBody>
</BEListingItemLightbox><BEListingItemLightbox isTemplate="1">
    <stf_ItemTeaserText><![CDATA[유레카 빌딩(Eureka building) 꼭대기의 유레카 89는 360도 전망 속에서 세련된 인테리어와 음식을 즐길 수 있는 최고의 행사 공간입니다. ]]></stf_ItemTeaserText>
    <anc_ReadMoreLink><![CDATA[]]></anc_ReadMoreLink>
    <img_ItemImage><![CDATA[/contentimages/business-events/Thumb-med-Melbourne/IND_Eureka89_Melbourne.jpg]]></img_ItemImage>
    <img_LightboxImage><![CDATA[<img src="/contentimages/business-events/Light-box-Melbourne/IND_Eureka89_Melbourne.jpg" alt="Eureka Skydeck 88 and Eureka 89" class="primary" />]]></img_LightboxImage>
    <stf_ItemReadMoreLinkText><![CDATA[자세히 알아보기]]></stf_ItemReadMoreLinkText>
    <stf_ItemTitle><![CDATA[유레카 스카이데크 88(Eureka Skydeck 88)과 유레카 89(Eureka 89) ]]></stf_ItemTitle>
    <stf_LightboxEmailAddress><![CDATA[events@eureka89.com.au]]></stf_LightboxEmailAddress>
    <stf_LightboxEmailLabel><![CDATA[이메일]]></stf_LightboxEmailLabel>
    <stf_LightboxPartnerId><![CDATA[Eureka Skydeck 88 and Eureka 89]]></stf_LightboxPartnerId>
    <stf_LightboxWebsiteLabel><![CDATA[홈페이지]]></stf_LightboxWebsiteLabel>
    <stf_LightboxWebsiteURL><![CDATA[www.eureka89.com.au]]></stf_LightboxWebsiteURL>
    <txt_LightboxContentBody><![CDATA[<div class="head">
        <h4>유레카 스카이데크 88(Eureka Skydeck 88)과 유레카 89(Eureka 89) </h4>
        </div>
        <p>유레카 빌딩(Eureka building) 꼭대기의 유레카 89는 360도 전망 속에서 세련된 인테리어와 음식을 즐길 수 있는 최고의 행사 공간입니다. </p>
        <ul>
            <li><strong>전화: </strong>+61 3 9693 8889</li>
            <li><strong>팩스:</strong> +61 3 9693 8899</li>
        </ul>]]></txt_LightboxContentBody>
</BEListingItemLightbox><BEListingItemLightbox isTemplate="1">
    <stf_ItemTeaserText><![CDATA[중심가의 페더레이션 광장(Federation Square)은 실내외 행사장을 절묘하게 조합하여 연중 2,000여 개의 행사를 주최합니다.]]></stf_ItemTeaserText>
    <anc_ReadMoreLink><![CDATA[]]></anc_ReadMoreLink>
    <img_ItemImage><![CDATA[/contentimages/business-events/Thumb-med-Melbourne/STO_TVIC_923267_Fed-Square.jpg]]></img_ItemImage>
    <img_LightboxImage><![CDATA[<img src="/contentimages/business-events/Light-box-Melbourne/STO_TVIC_923267_Fed-Square.jpg" alt="Federation Square" class="primary" />]]></img_LightboxImage>
    <stf_ItemReadMoreLinkText><![CDATA[자세히 알아보기]]></stf_ItemReadMoreLinkText>
    <stf_ItemTitle><![CDATA[페더레이션 광장]]></stf_ItemTitle>
    <stf_LightboxEmailAddress><![CDATA[events@fedsquare.com]]></stf_LightboxEmailAddress>
    <stf_LightboxEmailLabel><![CDATA[이메일]]></stf_LightboxEmailLabel>
    <stf_LightboxPartnerId><![CDATA[Federation Square]]></stf_LightboxPartnerId>
    <stf_LightboxWebsiteLabel><![CDATA[홈페이지]]></stf_LightboxWebsiteLabel>
    <stf_LightboxWebsiteURL><![CDATA[www.federationsquare.com.au]]></stf_LightboxWebsiteURL>
    <txt_LightboxContentBody><![CDATA[<div class="head">
        <h4>페더레이션 광장</h4>
        </div>
        <p>중심가의 페더레이션 광장(Federation Square)은 실내외 행사장을 절묘하게 조합하여 연중 2,000여 개의 행사를 주최합니다.</p>
        <ul>
            <li><strong>전화: </strong>+61 3 9655 1900</li>
            <li><strong>팩스:</strong> +61 3 9663 3652</li>
        </ul>]]></txt_LightboxContentBody>
</BEListingItemLightbox><BEListingItemLightbox isTemplate="1">
    <stf_ItemTeaserText><![CDATA[멜번 컵 카니벌(Melbourne Cup Carnival)이 열리는 이곳은 경기가 있건 없건, 현대적 행사장 속에 역사적 분위기를 구현하고 있는 명소입니다. ]]></stf_ItemTeaserText>
    <anc_ReadMoreLink><![CDATA[]]></anc_ReadMoreLink>
    <img_ItemImage><![CDATA[/contentimages/business-events/Thumb-med-Melbourne/STO_TVIC_Flemington_Racecourse.jpg]]></img_ItemImage>
    <img_LightboxImage><![CDATA[<img src="/contentimages/business-events/Light-box-Melbourne/STO_TVIC_Flemington_Racecourse.jpg" alt="Flemington Racecourse" class="primary" />]]></img_LightboxImage>
    <stf_ItemReadMoreLinkText><![CDATA[자세히 알아보기]]></stf_ItemReadMoreLinkText>
    <stf_ItemTitle><![CDATA[플레밍턴 경마장(Flemington Racecourse)]]></stf_ItemTitle>
    <stf_LightboxEmailAddress><![CDATA[customerservice@vic.net.au]]></stf_LightboxEmailAddress>
    <stf_LightboxEmailLabel><![CDATA[이메일]]></stf_LightboxEmailLabel>
    <stf_LightboxPartnerId><![CDATA[Flemington Racecourse]]></stf_LightboxPartnerId>
    <stf_LightboxWebsiteLabel><![CDATA[홈페이지]]></stf_LightboxWebsiteLabel>
    <stf_LightboxWebsiteURL><![CDATA[www.vrc.net.au/flemington-venues]]></stf_LightboxWebsiteURL>
    <txt_LightboxContentBody><![CDATA[<div class="head">
        <h4>플레밍턴 경마장(Flemington Racecourse)</h4>
        </div>
        <p>멜번 컵 카니벌(Melbourne Cup Carnival)이 열리는 이곳은 경기가 있건 없건, 현대적 행사장 속에 역사적 분위기를 구현하고 있는 명소입니다. </p>
        <ul>
            <li><strong>전화: </strong>+61 3 8378 0888</li>
            <li><strong>팩스:</strong> +61 3 8376 5148</li>
        </ul>]]></txt_LightboxContentBody>
</BEListingItemLightbox><BEListingItemLightbox isTemplate="1">
    <stf_ItemTeaserText><![CDATA[데일즈포드 호수(Lake Daylesford)까지 이어지는 6에이커의 풍부하고 비옥한 정원의 고요함 속에서 휴식합니다. ]]></stf_ItemTeaserText>
    <anc_ReadMoreLink><![CDATA[]]></anc_ReadMoreLink>
    <img_ItemImage><![CDATA[/contentimages/business-events/Thumb-med-Melbourne/STO_TVIC_Daylesford_Lake_House.jpg]]></img_ItemImage>
    <img_LightboxImage><![CDATA[<img src="/contentimages/business-events/Light-box-Melbourne/STO_TVIC_Daylesford_Lake_House.jpg" alt="Lake House – Daylesford" class="primary" />]]></img_LightboxImage>
    <stf_ItemReadMoreLinkText><![CDATA[자세히 알아보기]]></stf_ItemReadMoreLinkText>
    <stf_ItemTitle><![CDATA[레이크 하우스(Lake House) - 데일즈포드(Daylesford)]]></stf_ItemTitle>
    <stf_LightboxEmailAddress><![CDATA[info@lakehouse.com.au]]></stf_LightboxEmailAddress>
    <stf_LightboxEmailLabel><![CDATA[이메일]]></stf_LightboxEmailLabel>
    <stf_LightboxPartnerId><![CDATA[Lake House – Daylesford]]></stf_LightboxPartnerId>
    <stf_LightboxWebsiteLabel><![CDATA[홈페이지]]></stf_LightboxWebsiteLabel>
    <stf_LightboxWebsiteURL><![CDATA[www.lakehouse.com.au]]></stf_LightboxWebsiteURL>
    <txt_LightboxContentBody><![CDATA[<div class="head">
        <h4>레이크 하우스(Lake House) - 데일즈포드(Daylesford)</h4>
        </div>
        <p>데일즈포드 호수(Lake Daylesford)까지 이어지는 6에이커의 풍부하고 비옥한 정원의 고요함 속에서 휴식합니다. </p>
        <ul>
            <li><strong>전화: </strong>+61 3 5348 3329</li>
            <li><strong>팩스:</strong> +61 3 5348 3995</li>
        </ul>]]></txt_LightboxContentBody>
</BEListingItemLightbox><BEListingItemLightbox isTemplate="1">
    <stf_ItemTeaserText><![CDATA[1861년 설립된 호주 최대의 공공 아트 갤러리로서, 두 지역에서 운영하며 현대적 실내외 행사 공간을 제공합니다.]]></stf_ItemTeaserText>
    <anc_ReadMoreLink><![CDATA[]]></anc_ReadMoreLink>
    <img_ItemImage><![CDATA[/contentimages/business-events/Thumb-med-Melbourne/TABE_1032365_National_Gallery_of_Vic.jpg]]></img_ItemImage>
    <img_LightboxImage><![CDATA[<img src="/contentimages/business-events/Light-box-Melbourne/TABE_1032365_National_Gallery_of_Vic.jpg" alt="National Gallery of Victoria" class="primary" />]]></img_LightboxImage>
    <stf_ItemReadMoreLinkText><![CDATA[자세히 알아보기]]></stf_ItemReadMoreLinkText>
    <stf_ItemTitle><![CDATA[빅토리아 국립 미술관(National Gallery of Victoria)]]></stf_ItemTitle>
    <stf_LightboxEmailAddress><![CDATA[info@peterrowland.com.au]]></stf_LightboxEmailAddress>
    <stf_LightboxEmailLabel><![CDATA[이메일]]></stf_LightboxEmailLabel>
    <stf_LightboxPartnerId><![CDATA[National Gallery of Victoria]]></stf_LightboxPartnerId>
    <stf_LightboxWebsiteLabel><![CDATA[홈페이지]]></stf_LightboxWebsiteLabel>
    <stf_LightboxWebsiteURL><![CDATA[www.ngv.vic.gov.au]]></stf_LightboxWebsiteURL>
    <txt_LightboxContentBody><![CDATA[<div class="head">
        <h4>빅토리아 국립 미술관(National Gallery of Victoria)</h4>
        </div>
        <p>1861년 설립된 호주 최대의 공공 아트 갤러리로서, 두 지역에서 운영하며 현대적 실내외 행사 공간을 제공합니다.</p>
        <ul>
            <li><strong>전화: </strong>+61 3 9825 0092</li>
            <li><strong>팩스:</strong> +61 3 8620 2443</li>
        </ul>]]></txt_LightboxContentBody>
</BEListingItemLightbox><BEListingItemLightbox isTemplate="1">
    <stf_ItemTeaserText><![CDATA[중심가에서 15분이면 도착하는 해안에 위치한 세인트 킬다 씨 배스(St Kilda Sea Baths)의 리퍼블리카와 앙코르는 세인트 킬다 해안의 전망을 자랑합니다. ]]></stf_ItemTeaserText>
    <anc_ReadMoreLink><![CDATA[]]></anc_ReadMoreLink>
    <img_ItemImage><![CDATA[/contentimages/business-events/Thumb-med-Melbourne/TABE_105129_StKilda.jpg]]></img_ItemImage>
    <img_LightboxImage><![CDATA[<img src="/contentimages/business-events/Light-box-Melbourne/TABE_105129_StKilda.jpg" alt="Encore & Republica St Kilda Beach" class="primary" />]]></img_LightboxImage>
    <stf_ItemReadMoreLinkText><![CDATA[자세히 알아보기]]></stf_ItemReadMoreLinkText>
    <stf_ItemTitle><![CDATA[앙코르 &amp; 리퍼블리카 세인트 킬다 비치(Encore &amp; Republica St Kilda Beach)]]></stf_ItemTitle>
    <stf_LightboxEmailAddress><![CDATA[info@encorestkilda.com.au]]></stf_LightboxEmailAddress>
    <stf_LightboxEmailLabel><![CDATA[이메일]]></stf_LightboxEmailLabel>
    <stf_LightboxPartnerId><![CDATA[Encore &amp; Republica St Kilda Beach]]></stf_LightboxPartnerId>
    <stf_LightboxWebsiteLabel><![CDATA[홈페이지]]></stf_LightboxWebsiteLabel>
    <stf_LightboxWebsiteURL><![CDATA[www.encorestkilda.com.au]]></stf_LightboxWebsiteURL>
    <txt_LightboxContentBody><![CDATA[<div class="head">
        <h4>앙코르 &amp; 리퍼블리카 세인트 킬다 비치(Encore &amp; Republica St Kilda Beach)</h4>
        </div>
        <p>중심가에서 15분이면 도착하는 해안에 위치한 세인트 킬다 씨 배스(St Kilda Sea Baths)의 리퍼블리카와 앙코르는 세인트 킬다 해안의 전망을 자랑합니다. </p>
        <ul>
            <li><strong>전화: </strong>+61 3 8598 9055</li>
            <li><strong>팩스:</strong> +61 3 9593 6859</li>
        </ul>]]></txt_LightboxContentBody>
</BEListingItemLightbox> 
    </con_gallery_items>
</BEGenericLightboxGallery>
    </con_Maincontent>
    <con_sidebar>
        <BENavPanelPageLinks isTemplate="1">
    <anc_links>
        <anc_link>
            <url><![CDATA[/businessevents/kor/where-to-go/melbourne/venues.xml]]></url>
            <stf_NavTitle><![CDATA[행사장 ]]></stf_NavTitle> 
            <stf_NavSubHeader><![CDATA[]]></stf_NavSubHeader>
        </anc_link>
        <anc_link>
            <url><![CDATA[/businessevents/kor/where-to-go/melbourne/accommodation.xml]]></url>
            <stf_NavTitle><![CDATA[숙박시설]]></stf_NavTitle> 
            <stf_NavSubHeader><![CDATA[]]></stf_NavSubHeader>
        </anc_link>
        <anc_link>
            <url><![CDATA[/businessevents/kor/where-to-go/melbourne/activities.xml]]></url>
            <stf_NavTitle><![CDATA[다양한 즐길거리]]></stf_NavTitle> 
            <stf_NavSubHeader><![CDATA[]]></stf_NavSubHeader>
        </anc_link>
        <anc_link>
            <url><![CDATA[/businessevents/kor/where-to-go/melbourne/itineraries.xml]]></url>
            <stf_NavTitle><![CDATA[여행 일정]]></stf_NavTitle> 
            <stf_NavSubHeader><![CDATA[]]></stf_NavSubHeader>
        </anc_link>
        <anc_link>
            <url><![CDATA[/businessevents/kor/where-to-go/melbourne/association-expertise.xml]]></url>
            <stf_NavTitle><![CDATA[협회 행사에 대한 전문성]]></stf_NavTitle> 
            <stf_NavSubHeader><![CDATA[]]></stf_NavSubHeader>
        </anc_link>
        <anc_link>
            <url><![CDATA[/businessevents/kor/where-to-go/melbourne/gallery.xml]]></url>
            <stf_NavTitle><![CDATA[갤러리]]></stf_NavTitle> 
            <stf_NavSubHeader><![CDATA[]]></stf_NavSubHeader>
        </anc_link>
        <anc_link>
            <url><![CDATA[/businessevents/kor/where-to-go/melbourne/key-contacts.xml]]></url>
            <stf_NavTitle><![CDATA[주요 연락처]]></stf_NavTitle> 
            <stf_NavSubHeader><![CDATA[]]></stf_NavSubHeader>
        </anc_link>
    </anc_links>
</BENavPanelPageLinks>
    </con_sidebar> 
</BELayoutT5>
    </conMainContent>
    <lstNavigation>
    </lstNavigation>
</BEBaseFoundation>