<?xml version="1.0" ?>
<ConsumerBaseFoundation pageID="14084" isTemplate="1">
    <breadcrumb>
        <element level="1">
            <headline><![CDATA[首頁]]></headline>
            <href><![CDATA[/zht/index.xml]]></href>
        </element>
<element level="2">
            <headline><![CDATA[探索]]></headline>
            <href><![CDATA[/zht/explore.xml]]></href>
        </element>
<element level="4">
            <headline><![CDATA[澳洲的區域及內陸活動]]></headline>
            <href><![CDATA[/zht/explore/australian-events/regional-outback-events.xml]]></href>
        </element>

    </breadcrumb>
    <img_background><![CDATA[/contentimages/explore-events-regional-and-outback-events-regional-and-outback-events.jpg]]></img_background>
    <hdl_Title><![CDATA[澳洲的區域及內陸活動]]></hdl_Title>
    <img_Banner><![CDATA[]]></img_Banner>
    <img_SearchThumbnail><![CDATA[/thumbnails/explore-events-regional-and-outback-events-search.jpg]]></img_SearchThumbnail>
    <img_Thumbnail><![CDATA[/contentimages/explore-events-regional-and-outback-events-regional-and-outback-events-th.jpg]]></img_Thumbnail>
    <opt_HideInBreadcrumbs><![CDATA[Show]]></opt_HideInBreadcrumbs>
    <opt_HidePage><![CDATA[no]]></opt_HidePage>
    <opt_hideTitle><![CDATA[]]></opt_hideTitle>
    <opt_hide_in_sitemap><![CDATA[no]]></opt_hide_in_sitemap>
    <opt_IncludeVideo><![CDATA[]]></opt_IncludeVideo>
    <opt_isHubPage><![CDATA[0]]></opt_isHubPage>
    <opt_isNewWindow><![CDATA[_self]]></opt_isNewWindow>
    <opt_PageLayout><![CDATA[]]></opt_PageLayout>
    <opt_PartnerLead><![CDATA[]]></opt_PartnerLead>
    <stf_description><![CDATA[探索澳洲區域活動和內陸活動，盼您前來參與。這些慶典獨一無二，您很難在別處體驗到。]]></stf_description>
    <stf_ExcludedCountries><![CDATA[]]></stf_ExcludedCountries>
    <stf_hideInXmlSitemap><![CDATA[]]></stf_hideInXmlSitemap>
    <stf_ImageLocation><![CDATA[Ord Valley Muster, WA. &copy; Caleb Davenport.]]></stf_ImageLocation>
    <stf_intro_title><![CDATA[]]></stf_intro_title>
    <stf_IsExternalSiteArticle><![CDATA[]]></stf_IsExternalSiteArticle>
    <stf_IsMobile><![CDATA[y]]></stf_IsMobile>
    <stf_keywords><![CDATA[內陸活動、內陸賽車]]></stf_keywords>
    <stf_LinkLearnMore><![CDATA[瞭解更多]]></stf_LinkLearnMore>
    <stf_NavigationTagLine><![CDATA[]]></stf_NavigationTagLine>
    <stf_PageHeading><![CDATA[]]></stf_PageHeading>
    <stf_TargetedCountries><![CDATA[]]></stf_TargetedCountries>
    <stf_TrackingTitle><![CDATA[]]></stf_TrackingTitle>
    <TA_Title><![CDATA[澳洲的區域及內陸活動 - 澳洲旅遊局]]></TA_Title>
    <txt_Intro>
        <![CDATA[]]>
    </txt_Intro>
    <txt_MobileContentOnly>
        <![CDATA[]]>
    </txt_MobileContentOnly>
    <txt_SpotlightTag>
        <![CDATA[]]>
    </txt_SpotlightTag>
    <txt_Teaser>
        <![CDATA[
        偏遠的澳洲內陸有各種獨特的澳洲活動。
    ]]>
    </txt_Teaser>
    <con_Body>
        <EventsLayout isTemplate="1">
    <con_Body>
        <TopCategoryHighlights isTemplate="1">
            <stf_Heading><![CDATA[澳洲的區域及內陸活動]]></stf_Heading>
            <stf_InformationTitle><![CDATA[]]></stf_InformationTitle>
            <txt_Information><![CDATA[
      澳洲人借助澳洲內陸廣袤的開闊空間，舉辦此地特有的獨特活動。 參加袋鼠島美食節（Kangaroo Island Gourmet Gallop）或愛麗絲泉駱駝杯（Alice Springs Camel Cup）。 《來自雪河的人》叢林節（Snowy River Bush Festival）、奧德河谷節（Ord Valley Muster）和埃薩山牛仔競技會（Moount Isa Rodeo）讓您一窺廣大澳洲叢林的生活。 在小牧場或葡萄園欣賞歌劇，或者在空氣清新的藍山（Blue Mountains）過七月聖誕節。 參加庫伯佩地澳寶節（Coober Pedy Opal Festival），進入地底尋寶。 品嚐南澳（South Australia）的內陸美食節（Tastes of the Outback），或參加昆士蘭（Queensland）有趣的伯茲維爾賽馬大會（Birdsville Races）。
    ]]></txt_Information>
            <con_CenterContent>
                <CenterContent isTemplate="1">
                    <hdl_Title><![CDATA[袋鼠島美食節（Kangaroo Island Gourmet Gallop）]]></hdl_Title>
                    <img_MainImage><![CDATA[<img src="/contentimages/explore-events-regional-outback-events-kangaroo-island-hl.jpg" alt="Kangaroo Island Gourmet Gallop">]]></img_MainImage>
                    <stf_Caption><![CDATA[袋鼠島美食節（Kangaroo Island Gourmet Gallop）]]></stf_Caption>
                    <anc_link><![CDATA[]]></anc_link>
                    <txt_Information>
                        <![CDATA[<strong>南澳（South Australia），袋鼠島（Kangaroo Island）<br />
      一月</strong><p>
      袋鼠島美食節（Kangaroo Island Gourmet Gallop）結合了美好的賽馬日，以及袋鼠島（Kangaroo Island）知名的美食土特產慶典，包括海鮮、羊肉、橄欖油、蜂蜜和當地葡萄酒。 這項活動有六場賽事，您可下注並盡情沉浸在鄉村賽事的氣氛中。 袋鼠島美食節賽馬俱樂部（Kangaroo Island Racing Club）是南澳（South Australia）風景最優美的賽道之一，坐落在澳洲第三大島，周圍的美麗環境未受人為破壞。 花一天參加賽馬然後住個幾天，欣賞島嶼上其他<a href="/zht/explore/icons/kangaroo-island.xml" target="_self">知名名勝</a>。
    </p>]]>
                    </txt_Information>
                </CenterContent><CenterContent isTemplate="1">
                    <hdl_Title><![CDATA[內陸美食節（Tastes of the Outback）]]></hdl_Title>
                    <img_MainImage><![CDATA[<img src="/contentimages/explore-events-regional-and-outback-tastes-outback-hl.jpg" alt="Tastes of the Outback">]]></img_MainImage>
                    <stf_Caption><![CDATA[內陸美食節（Tastes of the Outback）]]></stf_Caption>
                    <anc_link><![CDATA[]]></anc_link>
                    <txt_Information>
                        <![CDATA[<strong>南澳（South Australia）<br />
      3 月 - 4 月</strong><p>
      內陸美食節在每年 4 月以<a href="/zht/explore/icons/flinders.xml" target="_self">費蓮達山脈（Flinders Ranges）</a>和<a href="/zht/explore/icons/red-centre.xml" target="_self">內陸</a>為絕美背景，展開為期四天的老饕慶典。 內陸美食節從南邊的詹姆士鎮（Jamestown）到北邊的因納明卡（Innamincka）呈現南澳（South Australia）的精華，提供遊客機會盡情品嚐南澳（South Australia）著名的地區佳餚美食，以及世界級的娛樂活動。 騎駱駝到定點享用豪華燭光晚餐或看電影，在星空下學習烹飪。 澳洲露天餐會（Aussie Tea Cookout）是活動高潮，您可以在雄偉的費蓮達山脈（Flinders Ranges）旁享用營火晚餐。
    </p>]]>
                    </txt_Information>
                </CenterContent><CenterContent isTemplate="1">
                    <hdl_Title><![CDATA[澳洲品酒節（Aussie Wine Month）]]></hdl_Title>
                    <img_MainImage><![CDATA[<img src="/contentimages/explore-events-regional-and-outback-events-aussie-wine-month-hl.jpg" alt="Aussie Wine Month">]]></img_MainImage>
                    <stf_Caption><![CDATA[澳洲品酒節（Aussie Wine Month）]]></stf_Caption>
                    <anc_link><![CDATA[]]></anc_link>
                    <txt_Information>
                        <![CDATA[<strong>全國<br />
      4 月</strong><p>
      澳洲品酒節由澳洲葡萄酒協會（Wine Australia）籌劃，全國共有約 100 場活動、品酒會、促銷及慶祝會，推銷澳洲葡萄酒。 這項活動讓澳洲的葡萄酒業者群聚一堂，共同推銷澳洲葡萄酒的品質、多元化和價值，並證明澳洲地區已經成為享譽國際的高級葡萄酒產區。 歡迎澳洲葡萄酒愛好者共襄盛舉！提供塔斯曼尼亞（Tassie）黑皮諾（Pinot Noir）、亨特（Hunter）的賽美蓉（Semillon）、瑪格麗特河（Margaret River）的赤霞珠（Cabernet Sauvignon）、雅拉河谷（Yarra Valley）的霞多麗（Chardonnay）或芭蘿莎（Barossa）的設拉子（Shiraz）與六十多個指定<a href="/zht/about/australias-landscapes/australian-wineries.xml" target="_self">葡萄酒產區</a>的各種美酒。
    </p>]]>
                    </txt_Information>
                </CenterContent><CenterContent isTemplate="1">
                    <hdl_Title><![CDATA[塔斯曼尼亞 Targa 越野賽（Targa Tasmania）]]></hdl_Title>
                    <img_MainImage><![CDATA[<img src="/contentimages/explore-events-regional-and-outback-events-targa-tasmania-hl.jpg" alt="Targa Tasmania">]]></img_MainImage>
                    <stf_Caption><![CDATA[塔斯曼尼亞 Targa 越野賽（Targa Tasmania）]]></stf_Caption>
                    <anc_link><![CDATA[]]></anc_link>
                    <txt_Information>
                        <![CDATA[<strong>塔斯曼尼亞（Tasmania）<br />
      4 月</strong><p>
      300 輛全球最珍奇特異的車輛於 4 月時齊聚塔斯曼尼亞 Targa 越野賽，在刺激的瀝青跑道上繞著<a href="/zht/explore/states/tas.xml" target="_self">塔斯曼尼亞（Tasmania）</a>飆風競速！ 這場為期六天的賽事，專為精品跑車、旅行車和豪華旅行車而設計，以<a href="/zht/explore/cities/regional-cities/tas-launceston-devonport-burnie.xml" target="_self">朗賽斯頓（Launceston）</a>為起點，飛馳 2,000 多公里到達<a href="/zht/explore/cities/hobart.xml" target="_self">荷伯特（Hobart）</a>。 與世界冠軍及專屬觀眾區的名流一同喝采。 或是與車手們一起在風景如畫的小鎮午餐，比如喬治鎮（George Town）、什菲爾德（Sheffield）、聖海倫斯（St Helens）、德文港（Devonport）和新諾福克（New Norfolk）。 遊客甚至可以申請駕駛自己的跑車，參加這場風景優美的公路汽車賽，全球都會轉播這場賽事。
    </p>]]>
                    </txt_Information>
                </CenterContent><CenterContent isTemplate="1">
                    <hdl_Title><![CDATA[奧蘭芝美食週（Orange F.O.O.D Week）]]></hdl_Title>
                    <img_MainImage><![CDATA[<img src="/contentimages/explore-events-regional-and-outback-events-orange-food-week-hl.jpg" alt="Orange F.O.O.D Week">]]></img_MainImage>
                    <stf_Caption><![CDATA[奧蘭芝美食週（Orange F.O.O.D Week）]]></stf_Caption>
                    <anc_link><![CDATA[/zht/explore/events/nsw-orange-food-week.xml]]></anc_link>
                    <txt_Information>
                        <![CDATA[<strong>新南威爾斯（New South Wales），奧蘭芝（Orange）<br />
      4 月</strong><p>
      每年 4 月於新南威爾斯（New South Wales）的奧蘭芝（Orange）區域中央，會舉辦 10 天的奧蘭芝美食週。 這裡距離<a href="/zht/explore/cities/sydney.xml" target="_self">悉尼（Sydney）</a>不到四小時，遊客可以參加超過 60 個活動，品嚐該區知名的新鮮美味，並認識烹調出這些美食的大廚。 您可在葡萄園享用早餐、在蘋果園散步或在當地的著名餐館參加烹飪課。 享用大廚品評晚餐或化妝舞會。 官方活動結束時，務必進一步探索該區享譽國際的涼爽氣候葡萄酒莊。
    </p>]]>
                    </txt_Information>
                </CenterContent><CenterContent isTemplate="1">
                    <hdl_Title><![CDATA[《來自雪河的人》叢林節（Man from Snowy River Bush Festival）]]></hdl_Title>
                    <img_MainImage><![CDATA[<img src="/contentimages/explore-events-regional-and-outback-events-man-from-snowy-river-hl.jpg" alt="The Man from Snowy River Bush Festival">]]></img_MainImage>
                    <stf_Caption><![CDATA[《來自雪河的人》節（Man Snowy River Bush Festival）]]></stf_Caption>
                    <anc_link><![CDATA[]]></anc_link>
                    <txt_Information>
                        <![CDATA[<strong>維多利亞（Victoria），克里永（Corryong）<br />
      4 月</strong><p>
      《來自雪河的人》叢林節每年在維多利亞（Victoria）克里永（Corryong）舉行，地點就在<a href="/zht/explore/icons/alps.xml" target="_self">大雪山（Snowy Mountains）</a>山腳，位於墨爾本（Melbourne）和悉尼（Sydney）的中間點。 這個節慶是為了慶祝叢林民謠、技巧和傳統，也是獨特的叢林聚會，越野單車騎士、詩人、藝術家以及澳洲高地區（High Country）和開拓精神的愛好者，全都齊聚一堂。 每年四月，澳洲和全球遊客會聚集在此，慶祝高地區（High Country）的傳統和叢林文化，並向澳洲最知名詩歌《來自雪河的人》的經典比喻致敬。
    </p>]]>
                    </txt_Information>
                </CenterContent><CenterContent isTemplate="1">
                    <hdl_Title><![CDATA[坎培拉區葡萄酒豐收節（Canberra District Wine Harvest Festival）]]></hdl_Title>
                    <img_MainImage><![CDATA[<img src="/contentimages/explore-events-regional-and-outback-events-canberra-district-wine-harvest-festival-hl.jpg" alt="Canberra District Wine Harvest Festival">]]></img_MainImage>
                    <stf_Caption><![CDATA[坎培拉葡萄酒豐收節（Canberra Wine Harvest Festival）]]></stf_Caption>
                    <anc_link><![CDATA[]]></anc_link>
                    <txt_Information>
                        <![CDATA[<strong>澳洲首都領地（Australian Capital Territory），坎培拉（Canberra）與鄰近地區<br />
      4 月</strong><p>
      坎培拉區葡萄酒豐收節讓您有機會品嚐此區著名的涼爽氣候葡萄酒。 看看葡萄園的豐收季節，結實累累。 加入壓碎葡萄、製酒和品酒課程，或者單純品嚐特製的豐收節菜單美食佳釀。 品嚐去年藏酒的新上市葡萄酒，並試嚐今年的新釀酒。 坎培拉地區（Canberra District）產酒區約有 30 家酒莊，也是少數可以看到釀酒師和酒窖業主的產區。
    </p>]]>
                    </txt_Information>
                </CenterContent><CenterContent isTemplate="1">
                    <hdl_Title><![CDATA[阿蓋爾鑚石奧德河谷節（Argyle Diamonds Ord Valley Muster）]]></hdl_Title>
                    <img_MainImage><![CDATA[<img src="/contentimages/explore-events-regional-and-outback-events-argyle-diamonds-ord-valley-muster-hl_-_Copy.jpg" alt="Argyle Diamonds Ord Valley Muster">]]></img_MainImage>
                    <stf_Caption><![CDATA[阿蓋爾鑚石奧德河谷節（Argyle Diamonds Ord Valley Muster）]]></stf_Caption>
                    <anc_link><![CDATA[/zht/explore/events/wa-ord-valley-muster.xml]]></anc_link>
                    <txt_Information>
                        <![CDATA[<strong>西澳（Western Australia），庫努納拉（Kununurra）<br />
      5 月</strong><p>
      奧德河谷節是為期兩週的慶典，熱鬧慶祝<a href="/zht/explore/icons/kimberley.xml" target="_self">金伯利（Kimberley）</a>的當地生活。 加入幾萬名當地民眾的行列，參加在崎嶇地貌中所舉辦的超過 50 個活動。 穿好裝備，參加趣味四驅車叢林探險、游過阿蓋爾湖（Lake Argyle）；這是澳洲最大的人造湖泊。或者沿著挑戰性十足、800 公里長的<a href="/zht/explore/itineraries/wa-gibb-river-rd.xml" target="_self">吉布河路（Gibb River Road）</a>騎越野單車。 品嚐新鮮的金伯利（Kimberley）特產，享受原住民音樂和舞蹈。 參加派對、挖鑽石或到競技賽看狂野騎手比賽。 活動的盛大終章是金伯利月亮（Kimberley Moon）鄉村音樂會，在奧德河（Ord River）河畔舉行。
    </p>]]>
                    </txt_Information>
                </CenterContent><CenterContent isTemplate="1">
                    <hdl_Title><![CDATA[藍山七月聖誕（Blue Mountains Yulefest）]]></hdl_Title>
                    <img_MainImage><![CDATA[<img src="/contentimages/explore-events-regional-and-outback-events-blue-mountains-yulefest-hl.jpg" alt="Blue Mountains Yulefest">]]></img_MainImage>
                    <stf_Caption><![CDATA[藍山七月聖誕（Blue Mountains Yulefest）]]></stf_Caption>
                    <anc_link><![CDATA[/zht/explore/cities/sydney/nsw-bluemts-yulefest.xml]]></anc_link>
                    <txt_Information>
                        <![CDATA[<strong>新南威爾斯（New South Wales），藍山（Blue Mountains）<br />
      6 月 - 8 月</strong><p>
      每年 6 月到 8 月的南半球冬天，大家會前往藍山（Blue Mountains）過<a href="/zht/explore/cities/sydney/nsw-bluemts-yulefest.xml" target="_self">七月聖誕（Yulefest）</a>，重現北半球傳統白色聖誕節的氣氛和魅力。 清新冷冽的空氣與偶爾飄落的雪花讓<a href="/zht/explore/icons/blue-mountains.xml" target="_self">藍山（Blue Mountains）</a>令人為之驚艷，您可以享受熊熊火焰、燒烤晚餐、圍著鋼琴唱聖誕頌、舉辦正式舞會，甚至還能看到聖誕老人。 卡通巴（Katoomba）的街道在 6 月冬日奇跡節（Winter Magic Festival）時熱鬧非凡，遊行隊伍中有雜耍演員、特技演員、音樂家、舞者、合唱團、民謠歌手、街頭藝人、講故事的人和詩人。
    </p>]]>
                    </txt_Information>
                </CenterContent><CenterContent isTemplate="1">
                    <hdl_Title><![CDATA[拉塞特駱駝杯（Lasseters Camel Cup）]]></hdl_Title>
                    <img_MainImage><![CDATA[<img src="/contentimages/explore-events-regional-outback-events-lasseters-camel-cup-hl.jpg" alt="Lasseters Camel Cup">]]></img_MainImage>
                    <stf_Caption><![CDATA[拉塞特駱駝杯（Lasseters Camel Cup）]]></stf_Caption>
                    <anc_link><![CDATA[]]></anc_link>
                    <txt_Information>
                        <![CDATA[<strong>北領地（Northern Territory），愛麗絲泉（Alice Springs）<br />
      7 月</strong><p>
      一年一度的拉塞特駱駝杯吸引全球遊客前往<a href="/zht/explore/cities/alice-springs.xml" target="_self">愛麗絲泉（Alice Springs）</a>。 每年 7 月，選手騎著駱駝馳騁在塵土飛揚的內陸賽道，觀眾無不歡欣鼓舞。 在某場比賽中，選手會打扮成新郎趕到賽場中途，找到各自嬌羞的新娘，並將她們帶回終點。 在賽事之間，遊客可以參與人力車賽跑，或參加駱駝先生和小姐杯（Mr and Miss Camel Cup）選拔，成為賽場上最時尚的代表。 肚皮舞、美食攤位和酒吧令狂歡節的氣氛更為熱烈。
    </p>]]>
                    </txt_Information>
                </CenterContent><CenterContent isTemplate="1">
                    <hdl_Title><![CDATA[埃薩山牛仔競技會（Mount Isa Rotary Rodeo）]]></hdl_Title>
                    <img_MainImage><![CDATA[<img src="/contentimages/explore-events-regional-and-outback-events-mount-isa-rodeo-hl.jpg" alt="Mount Isa Rotary Rodeo">]]></img_MainImage>
                    <stf_Caption><![CDATA[埃薩山牛仔競技會（Mount Isa Rotary Rodeo）]]></stf_Caption>
                    <anc_link><![CDATA[]]></anc_link>
                    <txt_Information>
                        <![CDATA[<strong>昆士蘭（Queensland），埃薩山（Mount Isa）<br />
      8 月</strong><p>
      於內陸昆士蘭（Queensland）城市埃薩山（Mount Isa）舉辦的埃薩牛仔競技（Isa Rodeo）是南半球最盛大熱鬧的牛仔競技賽。 細緻浪漫的<a href="/zht/explore/icons/red-centre.xml" target="_self">澳洲內陸</a>與粗曠大膽的挖礦城鎮相遇且東部與西部交會，也是人和動物共同切磋的時機。 包羅萬象的活動包括騎牛、馴野馬、扳小牛，這個慶典吸引全國最棒的男女牛仔參與。 在競技週期間澳洲和海外遊客會聚集在埃薩山（Mount Isa），人口因此暴增兩倍，萬頭鑽動欣賞刺激、精采、展現原始力量的牛仔競技比賽。
    </p>]]>
                    </txt_Information>
                </CenterContent><CenterContent isTemplate="1">
                    <hdl_Title><![CDATA[奧迪哈密頓島賽艇週（Audi Hamilton Island Race Week）]]></hdl_Title>
                    <img_MainImage><![CDATA[<img src="/contentimages/explore-events-regional-and-outback-events-audi-hamilton-island-race-week-hl.jpg" alt="Audi Hamilton Island Race Week">]]></img_MainImage>
                    <stf_Caption><![CDATA[奧迪哈密頓島賽艇週（Audi Hamilton Island Race Week）]]></stf_Caption>
                    <anc_link><![CDATA[]]></anc_link>
                    <txt_Information>
                        <![CDATA[<strong>昆士蘭（Queensland），哈密頓島（Hamilton Island）<br />
      8 月</strong><p>
      8 月時來自全球的觀眾和男女遊艇駕駛駛向哈密頓島（Hamilton Island），參加澳洲最大的年度近海平底貨船賽艇：奧迪哈密頓島賽艇週。 這是國際賽艇界的盛事，因此無論是水上或陸上都有許多活動。
    </p><p>
      哈密頓島（Hamilton Island）位置完美，坐落在<a href="/zht/explore/icons/great-barrier-reef.xml" target="_self">大堡礁（Great Barrier Reef）</a>邊緣，位於昆士蘭（Queensland）的 74 個<a href="/zht/explore/itineraries/qld-whitsundays-sailing.xml" target="_self">降靈群島（Whitsundays Islands）</a>間，這裡有怡人的天氣、湛藍的海水、純淨的海灘、珊瑚礁，以及美食佳釀。 參加慶典和現場活動，包括名人主廚準備的美味餐點、服裝秀、高爾夫比賽和品酒。
    </p>]]>
                    </txt_Information>
                </CenterContent><CenterContent isTemplate="1">
                    <hdl_Title><![CDATA[托德河賽艇（Henley-on-Todd Regatta）]]></hdl_Title>
                    <img_MainImage><![CDATA[<img src="/contentimages/explore-events-regional-and-outback-events-henley-on-todd-hl.jpg" alt="Henley-on-Todd Regatta">]]></img_MainImage>
                    <stf_Caption><![CDATA[托德河賽艇（Henley-on-Todd Regatta）]]></stf_Caption>
                    <anc_link><![CDATA[/zht/explore/events/nt-henley-on-todd.xml]]></anc_link>
                    <txt_Information>
                        <![CDATA[<strong>北領地（Northern Territory），愛麗絲泉（Alice Springs）<br />
      8 月</strong><p>
      托德河賽艇是年度賽艇和划船比賽，比賽場地在愛麗絲泉（Alice Springs）的乾河床，獨一無二。 1960 年代此城鎮提議仿效劍橋和牛津大學著名的泰晤士河賽舟（Henley-on-Thames），舉辦賽艇活動。 愛麗絲泉（Alice Springs）的扶輪社（Rotary Club）接納了這個意見。 儘管此城鎮距離最大水域 1500 公里遠，但大家並未打消念頭。 現在這是<a href="/zht/explore/states/nt.xml" target="_self">北領地（Northern Territory）</a>歷史最悠久的活動，河中多沙的托德河（Todd River）每年成為瘋狂人造船的有趣賽道。
    </p>]]>
                    </txt_Information>
                </CenterContent><CenterContent isTemplate="1">
                    <hdl_Title><![CDATA[伯茲維爾賽馬大會（Birdsville Races）]]></hdl_Title>
                    <img_MainImage><![CDATA[<img src="/contentimages/explore-events-regional-and-outback-events-birdsville-races-hl.jpg" alt="Birdsville Races">]]></img_MainImage>
                    <stf_Caption><![CDATA[伯茲維爾賽馬大會（Birdsville Races）]]></stf_Caption>
                    <anc_link><![CDATA[]]></anc_link>
                    <txt_Information>
                        <![CDATA[<strong>昆士蘭（Queensland），伯茲維爾（Birdsville）<br />
      9 月</strong><p>
      這個賽馬大會又稱為「內陸墨爾本杯（Melbourne Cup of the Outback）」，每年有成千上萬的賽馬愛好者前往伯茲維爾（Birdsville）參與為期兩天的精采內陸賽馬和娛樂盛會；這個內陸小鎮位於辛普森沙漠（Simpson Desert）邊緣，距離南澳（South Australian）邊界北方八英哩。 來自澳洲各地的頂尖賽馬都會參加比賽，競爭夢寐以求的伯茲維爾杯（Birdsville Cup）和現金大獎。 第一屆伯茲維爾賽馬大會（Birdsville Races）在 1882 年舉辦，從此成為澳洲賽馬傳統，現在吸引全球各地的遊客前來參加。 募得的資金用來援助內陸的皇家飛行醫生服務所（Royal Flying Doctor Service）。
    </p>]]>
                    </txt_Information>
                </CenterContent><CenterContent isTemplate="1">
                    <hdl_Title><![CDATA[澳洲遠征之旅（Australasian Safari）]]></hdl_Title>
                    <img_MainImage><![CDATA[<img src="/contentimages/explore-events-regional-and-outback-events-australasian-safari-hl.jpg" alt="Australasian Safari">]]></img_MainImage>
                    <stf_Caption><![CDATA[澳洲遠征之旅（Australasian Safari）]]></stf_Caption>
                    <anc_link><![CDATA[]]></anc_link>
                    <txt_Information>
                        <![CDATA[
        <strong>西澳<br />
        9 月</strong>
        <p>為期七天的澳洲遠征之旅是亞太地區最考驗耐力的賽車活動。 這項越野賽車的賽道從<a href="/zht/explore/cities/perth.xml" target="_self">珀斯（Perth）</a>到<a href="/zht/explore/states/wa/wa-kalgoorlie.xml" target="_self">卡爾古利（Kalgoorlie）</a>延伸超過 3000 公里，穿越整個西澳（Western Australia）的金黃內陸，即使是最強悍的四驅車、賽車和四輪摩托車，這趟旅程也是最艱難的考驗。 參賽者從珀斯（Perth）出發前往杰羅頓（Geraldton），沿著海岸開至熱帶加拿芬（Carnarvon）和內陸，穿越整個加斯科因（Gascoyne）區，繞著肯尼迪山脈（Kennedy Ranges）前行往南抵達終點杰羅頓（Geraldton）。 觀眾可沿著部份賽道駕駛自己的四驅越野車或電單車，在指定點停下來盡情感受塵土飛揚的高速刺激。 </p>
    ]]>
                    </txt_Information>
                </CenterContent><CenterContent isTemplate="1">
                    <hdl_Title><![CDATA[葡萄園歌劇節（Opera in the Vineyards）]]></hdl_Title>
                    <img_MainImage><![CDATA[<img src="/contentimages/explore-events-regional-and-outback-events-opera-vineyards-hl.jpg" alt="Opera in the Vineyards">]]></img_MainImage>
                    <stf_Caption><![CDATA[葡萄園歌劇節（Opera in the Vineyards）]]></stf_Caption>
                    <anc_link><![CDATA[]]></anc_link>
                    <txt_Information>
                        <![CDATA[<strong>維多利亞（Victoria），雅拉河谷（Yarra Valley）; 新南威爾斯（New South Wales），獵人谷（Hunter Valley）<br />
      10 月</strong><p>
      10 月兩個週末時段葡萄園歌劇節（Opera in the Vineyards）會在澳洲最知名的兩個葡萄酒產區舉行，分別是<a href="/zht/explore/states/nsw/hunter-valley.xml" target="_self">獵人谷（Hunter Valley）</a>的溫德漢姆酒莊（Wyndham Estate），以及維多利亞（Victoria）<a href="/zht/about/australias-landscapes/wine-regions/yarra-valley.xml" target="_self">雅拉河谷（Yarra Valley）</a>的香東酒莊（Domaine Chandon）。 澳洲最知名的歌劇演員搭配葡萄園的絕美環境為背景，加上優質的食物美酒，讓這場盛宴成為不可錯過的體驗。 歡迎提早抵達，讓味蕾盡情沉浸在美食佳釀中。 在夕陽西下時，於葡萄園華麗開闊的露天劇場坐下，享受真正難忘的古典音樂之夜。
    </p>]]>
                    </txt_Information>
                </CenterContent><CenterContent isTemplate="1">
                    <hdl_Title><![CDATA[巨蟒冒險賽（Anaconda Adventure Race）]]></hdl_Title>
                    <img_MainImage><![CDATA[<img src="/contentimages/explore-events-regional-and-outback-events-anaconda-adventure-race-hl.jpg" alt="Anaconda Adventure Race">]]></img_MainImage>
                    <stf_Caption><![CDATA[巨蟒冒險賽（Anaconda Adventure Race）]]></stf_Caption>
                    <anc_link><![CDATA[]]></anc_link>
                    <txt_Information>
                        <![CDATA[<strong>昆士蘭（Queensland），魯沙（Noosa）; 西澳（Western Australia），奧古斯塔（Augusta）; 維多利亞（Victoria），洛恩（Lorne）<br />
      8 月、11 月、12 月</strong><p>
      精采的越野賽事巨蟒冒險賽是全球公認的世界最大冒險賽。 這場賽事在澳洲三個地點舉行，分別是昆士蘭（Queensland）的<a href="/zht/explore/states/qld/qld-noosa.xml" target="_self">魯沙（Noosa）</a>、維多利亞（Victoria）的洛恩（Lorne）以及西澳（Western Australia）的奧古斯塔（Augusta）。 所有全國系列的比賽包括游泳、划船、跑步與越野單車，荒野地區就是比賽舞台。 「參加巨蟒賽」已經成為全澳洲的習俗，每年有 1200 名參賽者加入。 觀眾可以遊覽當地許多名勝，逛逛市集攤販、品嚐美食佳釀，欣賞娛樂表演、現場音樂演奏等，每個地方都有不同樂趣。
    </p>]]>
                    </txt_Information>
                </CenterContent><CenterContent isTemplate="1">
                    <hdl_Title><![CDATA[美酒玫瑰爵士樂節（Wine, Roses and all that Jazz）]]></hdl_Title>
                    <img_MainImage><![CDATA[<img src="/contentimages/explore-events-regional-and-outback-events-wine-roses-all-that-jazz-hl.jpg" alt="Wine, Roses and all that Jazz">]]></img_MainImage>
                    <stf_Caption><![CDATA[美酒玫瑰爵士樂節（Wine, Roses and all that Jazz）]]></stf_Caption>
                    <anc_link><![CDATA[]]></anc_link>
                    <txt_Information>
                        <![CDATA[<strong>澳洲首都領地（Australian Capital Territory），坎培拉（Canberra）與鄰近地區<br />
      11 月</strong><p>
      坎培拉地區（Canberra District）超過 30 個酒窖，因為美酒玫瑰爵士樂節變得熱鬧非凡，現場有娛樂表演、美食、活動，當然還有品酒大會。 品嚐獲獎的紅、白酒，搭配該區美食，並在葡萄園中放鬆欣賞現場音樂表演。 來個酒莊巡禮，見見坎培拉（Canberra）熱情的釀酒師，從市中心出發僅需 45 分鐘車程。 美酒玫瑰爵士樂節（Wine, Roses and all that Jazz）是難得的機會，能看到澳洲獲獎葡萄酒的釀酒葡萄，並有機會品嚐美味的陳年酒。
    </p>]]>
                    </txt_Information>
                </CenterContent><CenterContent isTemplate="1">
                    <hdl_Title><![CDATA[瑞士馬克韋伯塔斯曼尼亞挑戰賽（Swisse Mark Webber Tasmanian Challenge）]]></hdl_Title>
                    <img_MainImage><![CDATA[<img src="/contentimages/explore-events-regional-and-outback-events-mark-webber-challenge-hl.jpg" alt="Swisse Mark Webber Tasmanian Challenge">]]></img_MainImage>
                    <stf_Caption><![CDATA[瑞士馬克韋伯挑戰賽（Swisse Mark Webber Challenge）]]></stf_Caption>
                    <anc_link><![CDATA[]]></anc_link>
                    <txt_Information>
                        <![CDATA[<strong>塔斯曼尼亞（Tasmania）<br />
      12 月</strong><p>
      瑞士馬克韋伯塔斯曼尼亞挑戰賽是頂級多項活動挑戰，活動為期五天，舉行地點橫跨塔斯曼尼亞（Tasmania）最美麗的地區，比賽範圍超過 350 公里。 參賽者要騎越野單車、划獨木舟和健行，每天都有不同的挑戰項目。 <a href="/zht/explore/states/tas.xml" target="_self">塔斯曼尼亞（Tasmania）</a>是澳洲的冒險之島。 塔斯曼尼亞（Tasmania）有超過三分之一的面積是列入保護的國家公園和世界遺產區，在挑戰賽中成為冒險愛好者的大舞台。 塔斯曼尼亞（Tasmania）擁有適合每個人的探險活動，包括或陸地或水上、極端或溫和的各式活動。 這場比賽將為馬克韋伯基金會（Mark Webber Foundation）籌募資金，以便支持澳洲的公益活動。
    </p>]]>
                    </txt_Information>
                </CenterContent>
            </con_CenterContent>
        </TopCategoryHighlights>
    </con_Body>
    <con_RHSModules>
        <EventsResultsRHS isTemplate="1">
    <!-- no user content -->
</EventsResultsRHS><Listing isTemplate="1">
<anc_List1><![CDATA[/zht/about/australias-landscapes/outback-australia.xml]]></anc_List1>
<anc_MoreLink><![CDATA[]]></anc_MoreLink>
<hdl_Title><![CDATA[更多關於澳洲旅遊的好主意]]></hdl_Title>
<img_Thumbnail><![CDATA[]]></img_Thumbnail>
<med_File><![CDATA[]]></med_File>
<opt_isNewWindow><![CDATA[]]></opt_isNewWindow>
<stf_externalLink><![CDATA[]]></stf_externalLink>
<stf_ExternalLinkTitle><![CDATA[]]></stf_ExternalLinkTitle>
<stf_IsExternalSiteArticle><![CDATA[]]></stf_IsExternalSiteArticle>
<stf_LinkLearnMore><![CDATA[]]></stf_LinkLearnMore>
<txt_Teaser><![CDATA[]]></txt_Teaser>
<opt_national_landscapes_id><![CDATA[]]></opt_national_landscapes_id>
<stf_hideInXmlSitemap><![CDATA[]]></stf_hideInXmlSitemap>
<stf_TargetedCountry><![CDATA[]]></stf_TargetedCountry>
<con_Banner></con_Banner>
<con_Body></con_Body>
<con_RHSModules></con_RHSModules>
<con_Category></con_Category>
<lst_Subpages></lst_Subpages>
</Listing><PlanYourVisit isTemplate="1">
<anc_AccommodationSearch><![CDATA[/zht/AccommodationSearch.aspx]]></anc_AccommodationSearch>
<anc_ASPSearch><![CDATA[/zht/plan/plan-your-trip/find-travel-agent.xml]]></anc_ASPSearch>
<anc_Attraction><![CDATA[/zht/AttractionSearchResults.aspx]]></anc_Attraction>
<anc_Destinfo><![CDATA[/zht/DestinfoSearchResults.aspx]]></anc_Destinfo>
<anc_EventsSearch><![CDATA[/zht/EventsSearch.aspx]]></anc_EventsSearch>
<anc_GeneralSearch><![CDATA[/zht/GeneralSearch.ignore]]></anc_GeneralSearch>
<anc_Hire><![CDATA[/zht/Hire.aspx]]></anc_Hire>
<anc_Info><![CDATA[/zht/InfoSearchResults.aspx]]></anc_Info>
<anc_More><![CDATA[]]></anc_More>
<anc_RestaurantSearch><![CDATA[/zht/RestaurantSearch.ignore]]></anc_RestaurantSearch>
<anc_Tour><![CDATA[/zht/TourSearchResults.aspx]]></anc_Tour>
<anc_Transport><![CDATA[/zht/Transport.aspx]]></anc_Transport>
<hdl_Title><![CDATA[規劃行程]]></hdl_Title>
<language><![CDATA[CHT]]></language>
<stf_Accomodation><![CDATA[]]></stf_Accomodation>
<stf_AreaFilter><![CDATA[]]></stf_AreaFilter>
<stf_Attractions><![CDATA[]]></stf_Attractions>
<stf_AussieSpecialist><![CDATA[]]></stf_AussieSpecialist>
<stf_Destinationinfo><![CDATA[]]></stf_Destinationinfo>
<stf_DomesticRegion><![CDATA[]]></stf_DomesticRegion>
<stf_Events><![CDATA[]]></stf_Events>
<stf_Hire><![CDATA[]]></stf_Hire>
<stf_Informationservices><![CDATA[]]></stf_Informationservices>
<stf_PlanYourVisitTitle><![CDATA[Plan Your Visit]]></stf_PlanYourVisitTitle>
<stf_StateFilter><![CDATA[]]></stf_StateFilter>
<stf_Tours><![CDATA[]]></stf_Tours>
<stf_Transport><![CDATA[]]></stf_Transport>
</PlanYourVisit>
    </con_RHSModules> 
</EventsLayout>
    </con_Body>
    <lst_Subpages>
    </lst_Subpages>
</ConsumerBaseFoundation>